wechat-notify.py
wechat_notify/__init__.py
wechat_notify/notify.py
wechat_notify/test.py
wechat_notify-1.0.dist-info/LICENSE
wechat_notify-1.0.dist-info/METADATA
wechat_notify-1.0.dist-info/WHEEL
wechat_notify-1.0.dist-info/entry_points.txt
wechat_notify-1.0.dist-info/top_level.txt
wechat_notify-1.0.dist-info/RECORD
