Metadata-Version: 2.1
Name: wechat-notify
Version: 1.0
Summary: notify you on Wechat when certain task is completed
Home-page: UNKNOWN
Author: Tab_version
Author-email: tabvision@bupt.edu.cn
License: UNKNOWN
Platform: UNKNOWN
Requires-Dist: requests
